odoo/addons/product_by_supplier/README.rst
odoo/addons/product_by_supplier/__init__.py
odoo/addons/product_by_supplier/__manifest__.py
odoo/addons/product_by_supplier/i18n/ca.po
odoo/addons/product_by_supplier/i18n/de.po
odoo/addons/product_by_supplier/i18n/el_GR.po
odoo/addons/product_by_supplier/i18n/es.po
odoo/addons/product_by_supplier/i18n/es_PE.po
odoo/addons/product_by_supplier/i18n/fi.po
odoo/addons/product_by_supplier/i18n/fr.po
odoo/addons/product_by_supplier/i18n/fr_FR.po
odoo/addons/product_by_supplier/i18n/gl.po
odoo/addons/product_by_supplier/i18n/hr.po
odoo/addons/product_by_supplier/i18n/hr_HR.po
odoo/addons/product_by_supplier/i18n/it.po
odoo/addons/product_by_supplier/i18n/nl.po
odoo/addons/product_by_supplier/i18n/nl_NL.po
odoo/addons/product_by_supplier/i18n/product_by_supplier.pot
odoo/addons/product_by_supplier/i18n/pt.po
odoo/addons/product_by_supplier/i18n/pt_BR.po
odoo/addons/product_by_supplier/i18n/ro.po
odoo/addons/product_by_supplier/i18n/sl.po
odoo/addons/product_by_supplier/i18n/vi_VN.po
odoo/addons/product_by_supplier/i18n/zh_CN.po
odoo/addons/product_by_supplier/models/__init__.py
odoo/addons/product_by_supplier/models/product_supplierinfo.py
odoo/addons/product_by_supplier/readme/CONTRIBUTORS.rst
odoo/addons/product_by_supplier/readme/DESCRIPTION.rst
odoo/addons/product_by_supplier/readme/USAGE.rst
odoo/addons/product_by_supplier/static/description/icon.png
odoo/addons/product_by_supplier/static/description/index.html
odoo/addons/product_by_supplier/static/images/product_supplier_info.png
odoo/addons/product_by_supplier/views/product_supplierinfo_view.xml
odoo11_addon_product_by_supplier-11.0.1.0.0.99.dev2.dist-info/METADATA
odoo11_addon_product_by_supplier-11.0.1.0.0.99.dev2.dist-info/RECORD
odoo11_addon_product_by_supplier-11.0.1.0.0.99.dev2.dist-info/WHEEL
odoo11_addon_product_by_supplier-11.0.1.0.0.99.dev2.dist-info/top_level.txt
